README.md
setup.py
open_waters/__init__.py
open_waters.egg-info/PKG-INFO
open_waters.egg-info/SOURCES.txt
open_waters.egg-info/dependency_links.txt
open_waters.egg-info/requires.txt
open_waters.egg-info/top_level.txt
open_waters/account/__init__.py
open_waters/client/__init__.py
open_waters/data/__init__.py
open_waters/dataset/__init__.py
open_waters/document/__init__.py
open_waters/error/__init__.py
open_waters/flow/__init__.py
open_waters/safe/__init__.py
open_waters/step/__init__.py