Metadata-Version: 2.1
Name: open-waters
Version: 0.9
Summary: UNKNOWN
Home-page: https://github.com/ArmadaChain/Open_Waters/tree/master/python/package/open_waters
Author: armada chain inc
Author-email: kent@armadachain.io
License: ISC
Keywords: hederahashgraph
Platform: UNKNOWN
Classifier: Development Status :: 5 - Production/Stable
Classifier: License :: OSI Approved :: ISC License (ISCL)
Classifier: Programming Language :: Python :: 3.6
